.gitignore
CHANGES.rst
CONTRIBUTORS.txt
MANIFEST.in
README.rst
README.txt
bootstrap.py
buildout.cfg
setup.py
collective/__init__.py
collective.recipe.i18noverrides.egg-info/PKG-INFO
collective.recipe.i18noverrides.egg-info/SOURCES.txt
collective.recipe.i18noverrides.egg-info/dependency_links.txt
collective.recipe.i18noverrides.egg-info/entry_points.txt
collective.recipe.i18noverrides.egg-info/namespace_packages.txt
collective.recipe.i18noverrides.egg-info/not-zip-safe
collective.recipe.i18noverrides.egg-info/requires.txt
collective.recipe.i18noverrides.egg-info/top_level.txt
collective/recipe/__init__.py
collective/recipe/i18noverrides/README.txt
collective/recipe/i18noverrides/__init__.py
collective/recipe/i18noverrides/tests/__init__.py
collective/recipe/i18noverrides/tests/test_docs.py
collective/recipe/i18noverrides/tests/translations/test-fr.po
collective/recipe/i18noverrides/tests/translations/test-nl.po