Metadata-Version: 1.0
Name: collective.recipe.i18noverrides
Version: 1.1
Summary: Override translations by putting some .po files in the i18n directory of the zope 2 instance
Home-page: https://github.com/collective/collective.recipe.i18noverrides
Author: Maurits van Rees
Author-email: m.van.rees@zestsoftware.nl
License: GPL
Keywords: i18n
Platform: UNKNOWN
Classifier: Framework :: Buildout
Classifier: Framework :: Plone
Classifier: Framework :: Plone :: 3.3
Classifier: Intended Audience :: Developers
Classifier: Topic :: Software Development :: Build Tools
Classifier: Topic :: Software Development :: Libraries :: Python Modules
Classifier: License :: OSI Approved :: GNU General Public License (GPL)
